pgpy/__init__.py
pgpy/_curves.py
pgpy/constants.py
pgpy/decorators.py
pgpy/errors.py
pgpy/memoryview.py
pgpy/pgp.py
pgpy/symenc.py
pgpy/types.py
pgpy/packet/__init__.py
pgpy/packet/fields.py
pgpy/packet/packets.py
pgpy/packet/types.py
pgpy/packet/subpackets/__init__.py
pgpy/packet/subpackets/signature.py
pgpy/packet/subpackets/types.py
pgpy/packet/subpackets/userattribute.py
PGPy-0.5.4.dist-info/LICENSE
PGPy-0.5.4.dist-info/METADATA
PGPy-0.5.4.dist-info/WHEEL
PGPy-0.5.4.dist-info/top_level.txt
PGPy-0.5.4.dist-info/RECORD
