Metadata-Version: 2.1
Name: PGPy
Version: 0.5.4
Summary: Pretty Good Privacy for Python
Home-page: https://github.com/SecurityInnovation/PGPy
Author: Michael Greene
Author-email: mgreene@securityinnovation.com
Maintainer: Security Innovation
Maintainer-email: opensource@securityinnovation.com
License: BSD
Project-URL: Documentation, https://pgpy.readthedocs.io/en/latest/
Project-URL: Bug Tracker, https://github.com/SecurityInnovation/PGPy/issues
Keywords: OpenPGP,PGP,Pretty Good Privacy,GPG,GnuPG,openpgp,pgp,gnupg,gpg,encryption,signature
Platform: UNKNOWN
Classifier: Development Status :: 4 - Beta
Classifier: Operating System :: POSIX :: Linux
Classifier: Operating System :: MacOS :: MacOS X
Classifier: Operating System :: Microsoft :: Windows
Classifier: Intended Audience :: Developers
Classifier: Programming Language :: Python
Classifier: Programming Language :: Python :: 3.9
Classifier: Programming Language :: Python :: 3.8
Classifier: Programming Language :: Python :: 3.7
Classifier: Programming Language :: Python :: 3.6
Classifier: Programming Language :: Python :: 3.5
Classifier: Programming Language :: Python :: 3.4
Classifier: Programming Language :: Python :: 2.7
Classifier: Programming Language :: Python :: Implementation :: CPython
Classifier: Topic :: Security
Classifier: Topic :: Security :: Cryptography
Classifier: Topic :: Software Development :: Libraries
Classifier: Topic :: Software Development :: Libraries :: Python Modules
Classifier: License :: OSI Approved :: BSD License
Requires-Python: !=3.0.*,!=3.1.*,!=3.2.*,!=3.3.*,>=2.7
